hue2mqtt/__init__.py
hue2mqtt/__main__.py
hue2mqtt/app.py
hue2mqtt/config.py
hue2mqtt/discovery.py
hue2mqtt/hue2mqtt.py
hue2mqtt/messages.py
hue2mqtt/mqtt/__init__.py
hue2mqtt/mqtt/topic.py
hue2mqtt/mqtt/wrapper.py
hue2mqtt/py.typed
hue2mqtt/schema.py
hue2mqtt-0.4.2.dist-info/LICENSE
hue2mqtt-0.4.2.dist-info/METADATA
hue2mqtt-0.4.2.dist-info/WHEEL
hue2mqtt-0.4.2.dist-info/entry_points.txt
hue2mqtt-0.4.2.dist-info/RECORD
