Metadata-Version: 2.1
Name: hue2mqtt
Version: 0.4.2
Summary: Python Hue to MQTT Bridge
Home-page: https://github.com/trickeydan/hue2mqtt-python
License: MIT
Author: Dan Trickey
Author-email: contact@trickey.io
Requires-Python: >=3.8,<4.0
Classifier: License :: OSI Approved :: MIT License
Classifier: Programming Language :: Python :: 3
Classifier: Programming Language :: Python :: 3.8
Classifier: Programming Language :: Python :: 3.9
Classifier: Programming Language :: Python :: 3.10
Classifier: Programming Language :: Python :: 3.11
Classifier: Programming Language :: Python :: 3.12
Classifier: Topic :: Software Development :: Libraries :: Python Modules
Classifier: Typing :: Typed
Requires-Dist: aiohttp (>=3.8.1,<4.0.0)
Requires-Dist: aiohue (>=2.5.1,<3.0.0)
Requires-Dist: click (>=8.1.3,<9.0.0)
Requires-Dist: gmqtt (>=0.6.10,<0.7.0)
Requires-Dist: pydantic (>=1.9.2,<2.0.0)
Requires-Dist: tomli (>=2.0.1,<3.0.0) ; python_full_version <= "3.11.0"
Project-URL: Documentation, https://github.com/trickeydan/hue2mqtt-python
Project-URL: Repository, https://github.com/trickeydan/hue2mqtt-python
